tibet_audit/__init__.py
tibet_audit/checkpoint.py
tibet_audit/cli.py
tibet_audit/mercury.py
tibet_audit/runtime.py
tibet_audit/scanner.py
tibet_audit/signoff.py
tibet_audit/checks/__init__.py
tibet_audit/checks/ai_act.py
tibet_audit/checks/appi.py
tibet_audit/checks/base.py
tibet_audit/checks/gdpr.py
tibet_audit/checks/gulf_pdpl.py
tibet_audit/checks/health.py
tibet_audit/checks/humotica_pillars.py
tibet_audit/checks/jis.py
tibet_audit/checks/lgpd.py
tibet_audit/checks/ndpr.py
tibet_audit/checks/nis2.py
tibet_audit/checks/pdpa.py
tibet_audit/checks/penguin_act.py
tibet_audit/checks/pipa.py
tibet_audit/checks/privacy_act_au.py
tibet_audit/checks/provider_security.py
tibet_audit/checks/sovereignty.py
tibet_audit/checks/ucp.py
tibet_audit/exporters/__init__.py
tibet_audit/exporters/soc2.py
tibet_audit/frameworks/__init__.py
tibet_audit/frameworks/bio2.py
tibet_audit/frameworks/dora.py
tibet_audit/integrations/__init__.py
tibet_audit/integrations/checkov_adapter.py
tibet_audit-0.15.0.dist-info/METADATA
tibet_audit-0.15.0.dist-info/WHEEL
tibet_audit-0.15.0.dist-info/entry_points.txt
tibet_audit-0.15.0.dist-info/RECORD
