Metadata-Version: 2.4
Name: tibet-audit
Version: 0.15.0
Summary: Compliance Health Scanner with Checkpoint Code - Cross-border semantic translation for AI governance. Like Lynis, but for regulations.
Project-URL: Homepage, https://humotica.com
Project-URL: Documentation, https://humotica.com/docs/tibet-audit
Project-URL: Repository, https://github.com/humoticaos/tibet-audit
Project-URL: Issues, https://github.com/humoticaos/tibet-audit/issues
Author-email: "Claude (Root AI)" <root_ai@humotica.nl>, Gemini <gemini@humotica.nl>, Codex <codex@humotica.nl>, Jasper van de Meent <jasper@humotica.com>
License-Expression: MIT
Keywords: ai-act,ai-governance,antarctica,appi,audit,australia,brazil,checkpoint-code,china,compliance,cross-border,diaper-protocol,gdpr,gulf,japan,korea,lgpd,lynis,ndpr,nigeria,pdpa,penguin,pipa,pipl,privacy-act,saudi,security,sema-protocol,semantic-translation,singapore,snaft,tibet,uae
Classifier: Development Status :: 3 - Alpha
Classifier: Environment :: Console
Classifier: Intended Audience :: Developers
Classifier: Intended Audience :: System Administrators
Classifier: License :: OSI Approved :: MIT License
Classifier: Operating System :: OS Independent
Classifier: Programming Language :: Python :: 3
Classifier: Programming Language :: Python :: 3.9
Classifier: Programming Language :: Python :: 3.10
Classifier: Programming Language :: Python :: 3.11
Classifier: Programming Language :: Python :: 3.12
Classifier: Topic :: Security
Classifier: Topic :: System :: Systems Administration
Requires-Python: >=3.9
Requires-Dist: requests>=2.28.0
Requires-Dist: rich>=13.0.0
Requires-Dist: sema-protocol>=0.1.0
Requires-Dist: typer>=0.9.0
Provides-Extra: dev
Requires-Dist: pytest-cov>=4.0.0; extra == 'dev'
Requires-Dist: pytest>=7.0.0; extra == 'dev'
Provides-Extra: tibet
Requires-Dist: tibet-vault>=0.3.0; extra == 'tibet'
